purgatory/__init__.py
purgatory/domain/__init__.py
purgatory/domain/messages/__init__.py
purgatory/domain/messages/base.py
purgatory/domain/messages/commands.py
purgatory/domain/messages/events.py
purgatory/domain/model.py
purgatory/py.typed
purgatory/service/__init__.py
purgatory/service/_async/__init__.py
purgatory/service/_async/circuitbreaker.py
purgatory/service/_async/message_handlers.py
purgatory/service/_async/messagebus.py
purgatory/service/_async/repository.py
purgatory/service/_async/unit_of_work.py
purgatory/service/_redis.py
purgatory/service/_sync/__init__.py
purgatory/service/_sync/circuitbreaker.py
purgatory/service/_sync/message_handlers.py
purgatory/service/_sync/messagebus.py
purgatory/service/_sync/repository.py
purgatory/service/_sync/unit_of_work.py
purgatory/service/typing.py
purgatory/typing.py
purgatory_circuitbreaker-0.7.2.dist-info/LICENSE
purgatory_circuitbreaker-0.7.2.dist-info/WHEEL
purgatory_circuitbreaker-0.7.2.dist-info/METADATA
purgatory_circuitbreaker-0.7.2.dist-info/RECORD
